MANIFEST.in
README.md
RELEASE
setup.py
LiBis/Format.py
LiBis/NumExtractor.py
LiBis/__init__.py
LiBis/bedtools.py
LiBis/bsplot.py
LiBis/clipmode.py
LiBis/computeProcess.py
LiBis/fastqc.py
LiBis/mapreduce.py
LiBis/moabs.py
LiBis/pairend.py
LiBis/result.html
LiBis/simulation_script.py
LiBis/trim.py
LiBis/utils.py
LiBis.egg-info/PKG-INFO
LiBis.egg-info/SOURCES.txt
LiBis.egg-info/dependency_links.txt
LiBis.egg-info/requires.txt
LiBis.egg-info/top_level.txt
LiBis/chromsize/hg19.chrom.sizes
LiBis/chromsize/hg38.chrom.sizes
LiBis/chromsize/mm10.chrom.sizes
LiBis/chromsize/mm9.chrom.sizes
LiBis/jslib/datatables.css
LiBis/jslib/datatables.js
LiBis/jslib/datatables.min.css
LiBis/jslib/datatables.min.js
LiBis/jslib/DataTables/jquery.dataTables.min.js
LiBis/jslib/jQuery-3.3.1/jquery-3.3.1.min.js
bin/LiBis