Metadata-Version: 1.2
Name: LiBis
Version: 0.1.5.8
Summary: Low input Bisulfite sequencing alignment
Home-page: https://github.com/Dangertrip/LiBis
Author: Yue Yin
Author-email: dangertrip@tamu.edu
Maintainer: Deqiang Sun
Maintainer-email: dsun@tamu.edu
License: MIT
Platform: all
